{
    "altadefinizione01": "https://www.altadefinizione01.green",
    "altadefinizione01_link": "https://altadefinizione01.energy",
    "altadefinizioneclick": "https://altadefinizione.vote",
    "animealtadefinizione": "https://www.animealtadefinizione.it",
    "animeforce": "https://ww1.animeforce.org",
    "animeleggendari": "https://animeora.com",
    "animesaturn": "https://www.animesaturn.it",
    "animestream": "https://www.animeworld.tv",
    "animesubita": "http://www.animesubita.org",
    "animetubeita": "http://www.animetubeita.com",
    "animeunity": "https://www.animeunity.it",
    "animeuniverse": "https://www.animeuniverse.it/",
    "animeworld": "https://www.animeworld.tv",
    "casacinema": "https://www.casacinema.page",
    "cb01anime": "https://www.cineblog01.red",
    "cinemalibero": "https://www.cinemalibero.run",
    "cinetecadibologna": "http://cinestore.cinetecadibologna.it",
    "dreamsub": "https://dreamsub.stream",
    "dsda": "https://www.dsda.press",
    "fastsubita": "https://fastsubita.online",
    "filmgratis": "https://www.filmaltadefinizione.tv",
    "filmigratis": "https://filmigratis.org",
    "filmpertutti": "https://www.filmpertutti.icu",
    "filmsenzalimiticc": "https://www.filmsenzalimiti01.casa",
    "filmstreaming01": "https://filmstreaming01.com",
    "guardaserie_stream": "https://guardaserie.store",
    "guardaseriecam": "https://guardaserie.cam",
    "guardaserieclick": "https://www.guardaserie.guru",
    "guardaserieicu": "https://guardaserie.icu",
    "hd4me": "https://hd4me.net",
    "ilgeniodellostreaming": "https://ilgeniodellostreaming.lc",
    "ilgeniodellostreaming_cam": "https://ilgeniodellostreaming.cam",
    "italiaserie": "https://italiaserie.org",
    "mondoserietv": "https://mondoserietv.com",
    "piratestreaming": "https://www.piratestreaming.cloud",
    "polpotv": "https://polpotv.life",
    "raiplay": "https://www.raiplay.it",
    "seriehd": "https://seriehd.group",
    "serietvonline": "https://serietvonline.pw",
    "serietvsubita": "http://serietvsubita.xyz",
    "serietvu": "https://www.serietvu.link",
    "streamingcommunity": "https://streamingcommunity.to",
    "streamtime": "https://t.me/s/StreamTime",
    "tantifilm": "https://www.tantifilm.fit",
    "toonitalia": "https://toonitalia.org",
    "vvvvid": "https://www.vvvvid.it"
}